{
  "customCards:DefaultCommonAttack": {
    "NAME": "Strike",
    "DESCRIPTION": "Deal !D! damage. NL [#0000ff]This[] [#ff0000]Is[] [#ffff00]How[] [#88888]color[] [#ff00ff]works.[]"
  },
  "customCards:DefaultCommonSkill": {
    "NAME": "Defend",
    "DESCRIPTION": "Gain !B! Block. NL customCards:Multiword_Keyword."
  },
  "customCards:DefaultCommonPower": {
    "NAME": "Hold Place",
    "DESCRIPTION": "Gain !M! customCards:Keyword.",
    "UPGRADE_DESCRIPTION": "Gain !M! customcards:Keywords."
  },
  "customCards:DefaultUncommonAttack": {
    "NAME": "Big slap",
    "DESCRIPTION": "Deal !D! damage."
  },
  "customCards:DefaultUncommonSkill": {
    "NAME": "A Better Defend",
    "DESCRIPTION": "Gain !B! Plated Armor. Affected by Dexterity."
  },
  "customCards:DefaultUncommonPower": {
    "NAME": "Weirdness",
    "DESCRIPTION": "Gain X customcards:Keywords.",
    "UPGRADE_DESCRIPTION": "Gain X +1 customcards:Keywords."
  },
  "customCards:DefaultRareAttack": {
    "NAME": "TOUCH",
    "DESCRIPTION": "Deal !D! damage."
  },
  "customCards:DefaultRareSkill": {
    "NAME": "For Each Loop x2",
    "DESCRIPTION": "Apply !M! Vulnerable to all enemies, 2 times.",
    "UPGRADE_DESCRIPTION": "Apply !M! Vulnerable to all enemies, 3 times."
  },
  "customCards:DefaultRarePower": {
    "NAME": "In-Progress Form",
    "DESCRIPTION": "At the start of your turn, play a TOUCH."
  },
  "customCards:DefaultAttackWithVariable": {
    "NAME": "Special Strike",
    "DESCRIPTION": "Deal !D! damage [E] times. NL (Deal !customCards:ENERGY_DAMAGE! damage total.)"
  },
  "customCards:DefaultSecondMagicNumberSkill": {
    "NAME": "Cool 2 Number Card",
    "DESCRIPTION": "Apply !M! Vulnerable and !customCards:SecondMagic! poison to an enemy."
  },
  "customCards:OrbSkill": {
    "NAME": "Get Orb",
    "DESCRIPTION": "Channel 1 Default Orb."
  },
  "customCards:Telephone": {
    "NAME": "The Telephone",
    "DESCRIPTION": "Deal !D! customcards:Emotional_Damage"
  },
  "customCards:WhyAreWeStillHere": {
    "NAME": "Why are we still here?",
    "DESCRIPTION": "Gain !B! Block. Discard 4 cards at random"
  },
  "customCards:Blob": {
    "NAME": "Blob",
    "DESCRIPTION": "Deal !D! damage to everyone and apply 2 Vulnerable, 2 Poison and 2 Weakened"
  },
  "customCards:RadiationProtection": {
    "NAME": "5G Protection",
    "DESCRIPTION": "Gain 2 Dexterity and !B! Block"
  },
  "customCards:Balanced": {
    "NAME": "Balanced",
    "DESCRIPTION": "Deal !D! damage to everyone including yourself"
  },
  "customCards:Bitconnect": {
    "NAME": "BITCONNEEEECT",
    "DESCRIPTION": "Deal 70 times !D! damage NL Exhaust"
  },
  "customCards:FeatureRequest": {
    "NAME": "Feature Request",
    "DESCRIPTION": "Draw 5 cards and deal double damage next turn"
  },
  "customCards:LostInTranslation": {
    "NAME": "Lost in Translation",
    "DESCRIPTION": "What does this card do?"
  },
  "customCards:LowPolygon": {
    "NAME": "Compiling Shaders",
    "DESCRIPTION": "Deal !D! damage. NL Skip enemy turn. NL Ends your turn"
  },
  "customCards:TheCouncil": {
    "NAME": "The Council",
    "DESCRIPTION": "At the start of your turn, play 1 card. NL Gain 1 Dexterity for every card played.",
    "UPGRADE_DESCRIPTION": "At the start of your turn, play 2 cards. NL Gain 1 Dexterity for every card played."
  },
  "customCards:NothingToSeeHere": {
    "NAME": "Nothing to see here",
    "DESCRIPTION": ""
  },
  "customCards:PatienceHasLimits": {
    "NAME": "Patience has limits",
    "DESCRIPTION": "If 15 or more turns have passed, kill all enemies NL (1% chance to backfire)"
  },
  "customCards:TheProtagonist": {
    "NAME": "The Protagonist(?)",
    "DESCRIPTION": "When you would die, heal to 30 % of max HP",
    "UPGRADE_DESCRIPTION": "When you would die, heal to 50 % of max HP"
  },
  "customCards:TelephoneService": {
    "NAME": "Telephone Service",
    "DESCRIPTION": "Take up the phone, I know you're there NL Exhaust"
  },
  "customCards:SkipWorkDay": {
    "NAME": "Skip Workday",
    "DESCRIPTION": "Gain !B! Block and skip 1 day"
  },
  "customCards:Confused": {
    "NAME": "Confused",
    "DESCRIPTION": "Thinking... NL Ethereal"
  },
  "customCards:BigBrainEnergy": {
    "NAME": "Big Brain Energy",
    "DESCRIPTION": "Draw 1 card and work overtime"
  },
  "customCards:ShootingStar": {
    "NAME": "Starscourge",
    "DESCRIPTION": "Finishing move of Sep"
  },
  "customCards:DistortedReality": {
    "NAME": "Distorted Reality",
    "DESCRIPTION": "Gain !B! Block NL Skip 2 work days"
  }
}
